mcar.py
move_carrots/__init__.py
move_carrots/runner.py
move_carrots-0.1.1.dist-info/METADATA
move_carrots-0.1.1.dist-info/RECORD
move_carrots-0.1.1.dist-info/WHEEL
move_carrots-0.1.1.dist-info/top_level.txt
