Metadata-Version: 2.1
Name: move-carrots
Version: 0.1.1
Summary: Simple helper for reproducible (research) experiments.
Home-page: https://gitlab.com/Pinle/move-carrots
Author: Pinle
Author-email: 
License: MIT
Platform: UNKNOWN
Classifier: Programming Language :: Python :: 3
Classifier: License :: OSI Approved :: MIT License
Classifier: Operating System :: OS Independent
Requires-Dist: pyyaml
